projspec/__init__.py
projspec/__main__.py
projspec/_version.py
projspec/html.py
projspec/utils.py
projspec/artifact/__init__.py
projspec/artifact/base.py
projspec/artifact/container.py
projspec/artifact/installable.py
projspec/artifact/linter.py
projspec/artifact/process.py
projspec/artifact/python_env.py
projspec/content/__init__.py
projspec/content/base.py
projspec/content/cicd.py
projspec/content/data.py
projspec/content/env_var.py
projspec/content/environment.py
projspec/content/executable.py
projspec/content/license.py
projspec/content/metadata.py
projspec/content/package.py
projspec/proj/__init__.py
projspec/proj/backstage.py
projspec/proj/base.py
projspec/proj/briefcase.py
projspec/proj/conda_package.py
projspec/proj/conda_project.py
projspec/proj/datapackage.py
projspec/proj/documentation.py
projspec/proj/git.py
projspec/proj/helm.py
projspec/proj/hf.py
projspec/proj/ide.py
projspec/proj/node.py
projspec/proj/pixi.py
projspec/proj/poetry.py
projspec/proj/pyscript.py
projspec/proj/python_code.py
projspec/proj/rust.py
projspec/proj/uv.py
projspec-0.0.3.dist-info/METADATA
projspec-0.0.3.dist-info/WHEEL
projspec-0.0.3.dist-info/entry_points.txt
projspec-0.0.3.dist-info/licenses/LICENSE
projspec-0.0.3.dist-info/RECORD
