Metadata-Version: 2.4
Name: projspec
Version: 0.0.3
Summary: Project specification
Maintainer-email: Martin Durant <mdurant@anaconda.com>
License: BSD 3-Clause License
License-File: LICENSE
Keywords: project
Classifier: Development Status :: 4 - Beta
Classifier: Intended Audience :: Developers
Classifier: License :: OSI Approved :: BSD License
Classifier: Operating System :: OS Independent
Classifier: Programming Language :: Python :: 3.9
Classifier: Programming Language :: Python :: 3.10
Classifier: Programming Language :: Python :: 3.11
Classifier: Programming Language :: Python :: 3.12
Classifier: Programming Language :: Python :: 3.13
Requires-Python: >=3.9
Requires-Dist: click
Requires-Dist: fsspec>=2025.5.1
Requires-Dist: pyyaml
Requires-Dist: toml
Provides-Extra: test
Requires-Dist: pytest; extra == 'test'
Requires-Dist: pytest-cov; extra == 'test'
